eacu/__init__.py
eacu/main.py
eacu/layer/__init__.py
eacu/layer/lprint.py
eacu/layer/lp_impl/__init__.py
eacu/layer/lp_impl/log_impl.py
eacu/layer/lp_impl/print_impl.py
oarch/__init__.py
oarch/onion.py
oarch/onion_meta.py
onion/__init__.py
onion/onion.py
onion/onion_meta.py
eacu-0.1.1.dist-info/METADATA
eacu-0.1.1.dist-info/WHEEL
eacu-0.1.1.dist-info/top_level.txt
eacu-0.1.1.dist-info/RECORD
