Metadata-Version: 2.4
Name: eacu
Version: 0.1.1
Summary: Coder utils library for [Eagle's Baby]. *Do not install mammal.*
Author-email: 2229066748@qq.com
Maintainer: Eagle'sBaby
Maintainer-email: 2229066748@qq.com
License: Apache Licence 2.0
Keywords: python
Classifier: Programming Language :: Python
Classifier: Programming Language :: Python :: 3
Requires-Python: >=3.10
Requires-Dist: art>=6.5
Requires-Dist: loguru
Requires-Dist: onion-arch>=0.4.2
Dynamic: author-email
Dynamic: classifier
Dynamic: keywords
Dynamic: license
Dynamic: maintainer
Dynamic: maintainer-email
Dynamic: requires-dist
Dynamic: requires-python
Dynamic: summary
